{
  "cases": [],
  "clients": [],
  "staff": [],
  "sessions": [],
  "tasks": [],
  "payments": [],
  "documents": [],
  "attendance": [],
  "salaries": [],
  "sessionLogs": [],
  "clientGroups": [],
  "settings": {
    "githubRepo": "systeam-admin-ctrl/lawyer",
    "githubFilePath": "data.json",
    "autoSync": true,
    "lastSync": "٢٥‏/٦‏/٢٠٢٦، ٤:٣٦:٤٢ م",
    "lastSyncCommit": "5db9ddbdc6cb6b4f56ba54f85c012e9951beba0d"
  },
  "activityLog": [],
  "importantLinks": [],
  "courts": [],
  "version": "2.0",
  "expenses": [],
  "notifications": []
}